pyskycontrol/__init__.py
pyskycontrol/const.py
pyskycontrol/discover.py
pyskycontrol/helper.py
pyskycontrol/skydevice.py
pyskycontrol-2020.5.dist-info/LICENSE.txt
pyskycontrol-2020.5.dist-info/METADATA
pyskycontrol-2020.5.dist-info/WHEEL
pyskycontrol-2020.5.dist-info/top_level.txt
pyskycontrol-2020.5.dist-info/RECORD
